kdb/__init__.py
kdb/exceptions.py
kdb/common/__init__.py
kdb/common/config_parser.py
kdb/common/constants.py
kdb/common/encrypt_decrypt.py
kdb/common/mobile_manager.py
kdb/common/profiles.py
kdb/common/properties.py
kdb/common/random_util.py
kdb/common/ssh_connection.py
kdb/common/utils.py
kdb/config/__init__.py
kdb/config/device_list.py
kdb/config/proxy_list.py
kdb/config/settings.py
kdb/drivers/__init__.py
kdb/report/__init__.py
kdb/report/report_manager.py
kdb/report/test_case_log.py
kdb/report/test_step_log.py
kdb/scripts/__init__.py
kdb/unit_test/__init__.py
kdb/unit_test/mobile/__init__.py
kdb/unit_test/mobile/test_alert.py
kdb/unit_test/mobile/test_app.py
kdb/unit_test/mobile/test_be.py
kdb/unit_test/mobile/test_browser_navigation.py
kdb/unit_test/mobile/test_check.py
kdb/unit_test/mobile/test_click.py
kdb/unit_test/mobile/test_close_browser.py
kdb/unit_test/mobile/test_cookies.py
kdb/unit_test/mobile/test_double_click.py
kdb/unit_test/mobile/test_element_attribute.py
kdb/unit_test/mobile/test_execute_script.py
kdb/unit_test/mobile/test_is_display.py
kdb/unit_test/mobile/test_open_url.py
kdb/unit_test/mobile/test_press_keys.py
kdb/unit_test/mobile/test_press_keys_and_click.py
kdb/unit_test/mobile/test_select.py
kdb/unit_test/mobile/test_start_browser.py
kdb/unit_test/mobile/test_tap.py
kdb/unit_test/mobile/test_update_text.py
kdb/unit_test/mobile/test_verify_text_on_page.py
kdb/unit_test/mobile/test_verify_title.py
kdb/unit_test/mobile/test_verify_url_contains.py
kdb/unit_test/mobile/test_video.py
kdb/unit_test/mobile/test_window.py
kdb/unit_test/no_driver/__init__.py
kdb/unit_test/no_driver/test_command_line.py
kdb/unit_test/no_driver/test_files.py
kdb/unit_test/no_driver/test_global_var.py
kdb/unit_test/no_driver/test_json_path.py
kdb/unit_test/no_driver/test_random.py
kdb/unit_test/no_driver/test_requests.py
kdb/unit_test/no_driver/test_verify_string_contains.py
kdb/unit_test/pc/__init__.py
kdb/unit_test/pc/test_alert.py
kdb_testing-0.0.2.dist-info/LICENSE
kdb_testing-0.0.2.dist-info/METADATA
kdb_testing-0.0.2.dist-info/WHEEL
kdb_testing-0.0.2.dist-info/top_level.txt
kdb_testing-0.0.2.dist-info/RECORD
