Metadata-Version: 2.1
Name: kdb-testing
Version: 0.0.2
Summary: Automation testing
Home-page: https://github.com/Trucnt/kdb-core
Author: Truc Nguyen
Author-email: Truc Nguyen <trucnt88@gmail.com>
License: MIT
Project-URL: home-page, https://github.com/Trucnt/kdb-core
Classifier: Programming Language :: Python :: 3
Classifier: License :: OSI Approved :: MIT License
Classifier: Operating System :: OS Independent
Requires-Python: >=3.9
License-File: LICENSE
